{
  "Cache": "./cache",
  "Jails": [
    {
      "Title": "Kenton County Jail, KY",
      "Facility": "",
      "State": "KY",
      "Slug": "Kenton_County_KY",
      "Usable": true,
      "HasAdvancedSearch": true,
      "IndexURL": "https://omsweb.public-safety-cloud.com/jtclientweb/jailtracker/index/Kenton_County_KY",
      "FacilityURL": "",
      "Notes": "",
      "BaseURL": "https://omsweb.public-safety-cloud.com"
    },
    {
      "Title": "Grant County Jail, KY",
      "Facility": "",
      "State": "KY",
      "Slug": "Grant_County_Ky",
      "Usable": true,
      "HasAdvancedSearch": false,
      "IndexURL": "https://omsweb.public-safety-cloud.com/jtclientweb/jailtracker/index/Grant_County_Ky",
      "FacilityURL": "",
      "Notes": "",
      "BaseURL": "https://omsweb.public-safety-cloud.com"
    },
    {
      "Title": "Ohio County Detention Center, KY",
      "Facility": "",
      "State": "KY",
      "Slug": "OHIO_COUNTY_KY",
      "Usable": true,
      "HasAdvancedSearch": false,
      "IndexURL": "https://omsweb.public-safety-cloud.com/jtclientweb/jailtracker/index/OHIO_COUNTY_KY",
      "FacilityURL": "",
      "Notes": "",
      "BaseURL": "https://omsweb.public-safety-cloud.com"
    },
    {
      "Title": "Logan County Detention Center, KY",
      "Facility": "",
      "State": "KY",
      "Slug": "LOGAN_COUNTY_KY",
      "Usable": true,
      "HasAdvancedSearch": true,
      "IndexURL": "https://omsweb.public-safety-cloud.com/jtclientweb/jailtracker/index/LOGAN_COUNTY_KY",
      "FacilityURL": "",
      "Notes": "",
      "BaseURL": "https://omsweb.public-safety-cloud.com"
    },
    {
      "Title": "Leslie County Detention Center, KY",
      "Facility": "",
      "State": "KY",
      "Slug": "LESLIE_COUNTY_KY",
      "Usable": true,
      "HasAdvancedSearch": false,
      "IndexURL": "https://omsweb.public-safety-cloud.com/jtclientweb/jailtracker/index/LESLIE_COUNTY_KY",
      "FacilityURL": "",
      "Notes": "",
      "BaseURL": "https://omsweb.public-safety-cloud.com"
    },
    {
      "Title": "Oldham County Jail, KY",
      "Facility": "",
      "State": "KY",
      "Slug": "Oldham_County_Ky",
      "Usable": true,
      "HasAdvancedSearch": false,
      "IndexURL": "https://omsweb.public-safety-cloud.com/jtclientweb/jailtracker/index/Oldham_County_Ky",
      "FacilityURL": "",
      "Notes": "",
      "BaseURL": "https://omsweb.public-safety-cloud.com"
    },
    {
      "Title": "Knox County Detention Center, KY",
      "Facility": "",
      "State": "KY",
      "Slug": "KNOX_COUNTY_KY",
      "Usable": true,
      "HasAdvancedSearch": false,
      "IndexURL": "https://omsweb.public-safety-cloud.com/jtclientweb/jailtracker/index/KNOX_COUNTY_KY",
      "FacilityURL": "",
      "Notes": "",
      "BaseURL": "https://omsweb.public-safety-cloud.com"
    },
    {
      "Title": "Henderson Co. Jail, KY",
      "Facility": "",
      "State": "KY",
      "Slug": "HENDERSON_COUNTY_KY",
      "Usable": true,
      "HasAdvancedSearch": true,
      "IndexURL": "https://omsweb.public-safety-cloud.com/jtclientweb/jailtracker/index/HENDERSON_COUNTY_KY",
      "FacilityURL": "",
      "Notes": "",
      "BaseURL": "https://omsweb.public-safety-cloud.com"
    },
    {
      "Title": "Clark Co Det Center, KY",
      "Facility": "",
      "State": "KY",
      "Slug": "Clark_County_Ky",
      "Usable": true,
      "HasAdvancedSearch": false,
      "IndexURL": "https://omsweb.public-safety-cloud.com/jtclientweb/jailtracker/index/Clark_County_Ky",
      "FacilityURL": "",
      "Notes": "",
      "BaseURL": "https://omsweb.public-safety-cloud.com"
    },
    {
      "Title": "Daviess County Jail, KY",
      "Facility": "",
      "State": "KY",
      "Slug": "DAVIES_COUNTY_KY",
      "Usable": true,
      "HasAdvancedSearch": false,
      "IndexURL": "https://omsweb.public-safety-cloud.com/jtclientweb/jailtracker/index/DAVIES_COUNTY_KY",
      "FacilityURL": "",
      "Notes": "",
      "BaseURL": "https://omsweb.public-safety-cloud.com"
    },
    {
      "Title": "Scott County Detention Center, KY",
      "Facility": "",
      "State": "KY",
      "Slug": "Scott_County_KY",
      "Usable": true,
      "HasAdvancedSearch": false,
      "IndexURL": "https://omsweb.public-safety-cloud.com/jtclientweb/jailtracker/index/Scott_County_KY",
      "FacilityURL": "",
      "Notes": "",
      "BaseURL": "https://omsweb.public-safety-cloud.com"
    },
    {
      "Title": "Warren County Detention Center, KY",
      "Facility": "",
      "State": "KY",
      "Slug": "Warren_County_KY",
      "Usable": true,
      "HasAdvancedSearch": true,
      "IndexURL": "https://omsweb.public-safety-cloud.com/jtclientweb/jailtracker/index/Warren_County_KY",
      "FacilityURL": "",
      "Notes": "",
      "BaseURL": "https://omsweb.public-safety-cloud.com"
    },
    {
      "Title": "Pulaski County Detention Center, KY",
      "Facility": "",
      "State": "KY",
      "Slug": "PULASKI_COUNTY_KY",
      "Usable": true,
      "HasAdvancedSearch": false,
      "IndexURL": "https://omsweb.public-safety-cloud.com/jtclientweb/jailtracker/index/PULASKI_COUNTY_KY",
      "FacilityURL": "",
      "Notes": "",
      "BaseURL": "https://omsweb.public-safety-cloud.com"
    },
    {
      "Title": "Campbell County Jail KY",
      "Facility": "",
      "State": "KY",
      "Slug": "Campbell_County_KY",
      "Usable": true,
      "HasAdvancedSearch": false,
      "IndexURL": "https://omsweb.public-safety-cloud.com/jtclientweb/jailtracker/index/Campbell_County_KY",
      "FacilityURL": "",
      "Notes": "",
      "BaseURL": "https://omsweb.public-safety-cloud.com"
    },
    {
      "Title": "Rowan County Detention Center, KY",
      "Facility": "",
      "State": "KY",
      "Slug": "Rowan_County_KY",
      "Usable": true,
      "HasAdvancedSearch": false,
      "IndexURL": "https://omsweb.public-safety-cloud.com/jtclientweb/jailtracker/index/Rowan_County_KY",
      "FacilityURL": "",
      "Notes": "",
      "BaseURL": "https://omsweb.public-safety-cloud.com"
    },
    {
      "Title": "Marion County KY",
      "Facility": "",
      "State": "KY",
      "Slug": "Marion_County_KY",
      "Usable": true,
      "HasAdvancedSearch": false,
      "IndexURL": "https://omsweb.public-safety-cloud.com/jtclientweb/jailtracker/index/Marion_County_KY",
      "FacilityURL": "",
      "Notes": "",
      "BaseURL": "https://omsweb.public-safety-cloud.com"
    },
    {
      "Title": "Laurel County Jail, KY",
      "Facility": "",
      "State": "KY",
      "Slug": "Laurel_County_Ky",
      "Usable": true,
      "HasAdvancedSearch": true,
      "IndexURL": "https://omsweb.public-safety-cloud.com/jtclientweb/jailtracker/index/Laurel_County_Ky",
      "FacilityURL": "",
      "Notes": "",
      "BaseURL": "https://omsweb.public-safety-cloud.com"
    },
    {
      "Title": "Fulton County Jail, KY",
      "Facility": "Fulton County Jail",
      "State": "KY",
      "Slug": "FULTON_COUNTY_REGIONAL_KY",
      "Usable": true,
      "HasAdvancedSearch": true,
      "IndexURL": "https://omsweb.public-safety-cloud.com/jtclientweb/jailtracker/index/FULTON_COUNTY_REGIONAL_KY",
      "FacilityURL": "",
      "Notes": "",
      "BaseURL": "https://omsweb.public-safety-cloud.com"
    },
    {
      "Title": "Harlan County Detention Center, KY",
      "Facility": "",
      "State": "KY",
      "Slug": "HARLAN_COUNTY_KY",
      "Usable": true,
      "HasAdvancedSearch": true,
      "IndexURL": "https://omsweb.public-safety-cloud.com/jtclientweb/jailtracker/index/HARLAN_COUNTY_KY",
      "FacilityURL": "",
      "Notes": "",
      "BaseURL": "https://omsweb.public-safety-cloud.com"
    },
    {
      "Title": "Nelson County Jail, KY",
      "Facility": "",
      "State": "KY",
      "Slug": "Nelson_County_Ky",
      "Usable": true,
      "HasAdvancedSearch": false,
      "IndexURL": "https://omsweb.public-safety-cloud.com/jtclientweb/jailtracker/index/Nelson_County_Ky",
      "FacilityURL": "",
      "Notes": "",
      "BaseURL": "https://omsweb.public-safety-cloud.com"
    },
    {
      "Title": "Jessamine Co. Jail, KY",
      "Facility": "",
      "State": "KY",
      "Slug": "Jessamine_County_Ky",
      "Usable": true,
      "HasAdvancedSearch": false,
      "IndexURL": "https://omsweb.public-safety-cloud.com/jtclientweb/jailtracker/index/Jessamine_County_Ky",
      "FacilityURL": "",
      "Notes": "",
      "BaseURL": "https://omsweb.public-safety-cloud.com"
    },
    {
      "Title": "Bell County Detention Center, KY",
      "Facility": "",
      "State": "KY",
      "Slug": "Bell_County_KY",
      "Usable": true,
      "HasAdvancedSearch": true,
      "IndexURL": "https://omsweb.public-safety-cloud.com/jtclientweb/jailtracker/index/Bell_County_KY",
      "FacilityURL": "",
      "Notes": "",
      "BaseURL": "https://omsweb.public-safety-cloud.com"
    },
    {
      "Title": "Invalid Facility",
      "Facility": "Macomb County",
      "State": "MI",
      "Slug": "MACOMB_CO_MI",
      "Usable": false,
      "HasAdvancedSearch": false,
      "IndexURL": "https://omsweb.secure-gps.com/jtclientweb/jailtracker/index/MACOMB_CO_MI",
      "FacilityURL": "",
      "Notes": "Search required",
      "BaseURL": "https://omsweb.public-safety-cloud.com"
    },
    {
      "Title": "Hopkins Co. Jail, KY",
      "Facility": "",
      "State": "KY",
      "Slug": "HOPKINS_COUNTY_KY",
      "Usable": true,
      "HasAdvancedSearch": true,
      "IndexURL": "https://omsweb.public-safety-cloud.com/jtclientweb/jailtracker/index/HOPKINS_COUNTY_KY",
      "FacilityURL": "",
      "Notes": "",
      "BaseURL": "https://omsweb.public-safety-cloud.com"
    },
    {
      "Title": "Allen County Detention Center",
      "Facility": "",
      "State": "KY",
      "Slug": "ALLEN_COUNTY_KY",
      "Usable": true,
      "HasAdvancedSearch": true,
      "IndexURL": "https://omsweb.public-safety-cloud.com/jtclientweb/jailtracker/index/ALLEN_COUNTY_KY",
      "FacilityURL": "",
      "Notes": "",
      "BaseURL": "https://omsweb.public-safety-cloud.com"
    },
    {
      "Title": "Perry Co Sheriff IN",
      "Facility": "",
      "State": "IN",
      "Slug": "Perry_County_IN",
      "Usable": true,
      "HasAdvancedSearch": false,
      "IndexURL": "https://omsweb.public-safety-cloud.com/jtclientweb/jailtracker/index/Perry_County_IN",
      "FacilityURL": "",
      "Notes": "",
      "BaseURL": "https://omsweb.public-safety-cloud.com"
    },
    {
      "Title": "Atchison County KS",
      "Facility": "",
      "State": "KS",
      "Slug": "Atchison_County_KS",
      "Usable": true,
      "HasAdvancedSearch": true,
      "IndexURL": "https://omsweb.public-safety-cloud.com/jtclientweb/jailtracker/index/Atchison_County_KS",
      "FacilityURL": "",
      "Notes": "",
      "BaseURL": "https://omsweb.public-safety-cloud.com"
    }
  ]
}
